micropython_hs3003/__init__.py
micropython_hs3003/hs3003.py
micropython_hs3003-0.1.0.dist-info/LICENSE
micropython_hs3003-0.1.0.dist-info/METADATA
micropython_hs3003-0.1.0.dist-info/WHEEL
micropython_hs3003-0.1.0.dist-info/top_level.txt
micropython_hs3003-0.1.0.dist-info/RECORD
