Metadata-Version: 2.1
Name: micropython-hs3003
Version: 0.1.0
Summary: MicroPython Driver for the Renesas HS3003 Temperature and Humidity Sensor
Author-email: JDM <xxyx@mailmeto.mozmail.com>
License: MIT
Project-URL: Homepage, https://github.com/jposada202020/MicroPython_HS3003
Keywords: sensor,micropython,hs3003,micropython,driver,temperature,rensesas,hs3003,temperature,humidity,sensor
Classifier: Intended Audience :: Developers
Classifier: Topic :: Software Development :: Libraries
Classifier: Topic :: Software Development :: Embedded Systems
Classifier: Topic :: System :: Hardware
Classifier: License :: OSI Approved :: MIT License
Classifier: Programming Language :: Python :: Implementation :: MicroPython
License-File: LICENSE
